Workbook
Name Comapny.Name: Parameters!$G$2
Name D.F.Int.Exp: 'Debt Schedule'!$J$21:$N$21
Name D.F.LTDEBT: 'Debt Schedule'!$J$12:$N$12
Name D.F.STDebt: 'Debt Schedule'!$J$11:$N$11
Name D.F.Total.Debt: 'Debt Schedule'!$J$8:$N$8
Name D.H.Int.Expense: 'Debt Schedule'!$G$21:$I$21
Name D.H.LTDebt: 'Debt Schedule'!$G$12:$I$12
Name D.H.STDebt: 'Debt Schedule'!$G$11:$I$11
Name D.H.Total.Debt: 'Debt Schedule'!$G$8:$I$8
Name Discount: DCF!$G$27:$K$27
Name EV.Mult: DCF!$G$40
Name EV.Perp: DCF!$G$35
Name F.Assets: 'Financial Statements'!$J$58:$N$58
Name f.Capital: 'Financial Statements'!$J$80:$N$80
Name F.Cash: 'Financial Statements'!$J$113:$N$113
Name F.Cash.Financing: 'Financial Statements'!$J$109:$N$109
Name F.Cash.Investment: 'Financial Statements'!$J$102:$N$102
Name F.Cash.Ops: 'Financial Statements'!$J$97:$N$97
Name F.COGS: 'Financial Statements'!$J$13:$N$13
Name F.EBIT: 'Financial Statements'!$J$28:$N$28
Name F.EBITDA: DCF!$G$16:$K$16
Name F.Equity: 'Financial Statements'!$J$79:$N$79
Name F.LT.Assets: 'Financial Statements'!$J$57:$N$57
Name F.Margin: 'Financial Statements'!$J$15:$N$15
Name F.Net.Income: 'Financial Statements'!$J$36:$N$36
Name F.OpEx: 'Financial Statements'!$J$26:$N$26
Name F.Pref: 'Financial Statements'!$J$75:$N$75
Name f.revenues: 'Financial Statements'!$J$7:$N$7
Name F.ST.Assets: 'Financial Statements'!$J$48:$N$48
Name forecast.years: Parameters!$J$4
Name GFHIVM.Valuation: DCF!$H$64
Name H.Assets: 'Financial Statements'!$G$58:$I$58
Name H.Capital: 'Financial Statements'!$G$80:$I$80
Name H.Cash: 'Financial Statements'!$G$113:$I$113
Name H.Cash.Financing: 'Financial Statements'!$H$109:$I$109
Name H.Cash.Investment: 'Financial Statements'!$H$102:$I$102
Name H.Cash.Ops: 'Financial Statements'!$H$97:$I$97
Name H.COGS: 'Financial Statements'!$G$13:$I$13
Name H.EBIT: 'Financial Statements'!$G$28:$I$28
Name H.Equity: 'Financial Statements'!$G$79:$I$79
Name H.LT.Assets: 'Financial Statements'!$G$57:$I$57
Name H.Margin: 'Financial Statements'!$G$15:$I$15
Name H.Net.Income: 'Financial Statements'!$G$36:$I$36
Name H.Pref: 'Financial Statements'!$G$75:$I$75
Name H.Revenues: 'Financial Statements'!$G$7:$I$7
Name H.ST.Assets: 'Financial Statements'!$G$48:$I$48
Name market.cap: DCF!$G$6
Name NPV.FCF: DCF!$G$28
Name P.F.Accounts.Payable: Parameters!$J$38:$N$38
Name P.F.Accruds: Parameters!$J$39:$N$39
Name P.F.Accts.Rec.Days: Parameters!$J$35:$N$35
Name P.F.Amorization: Parameters!$J$26:$N$26
Name P.F.Buybacks: Parameters!$J$29:$N$29
Name P.F.CapEx: Parameters!$J$44:$N$44
Name P.F.COGS: Parameters!$J$14:$N$16
Name P.F.Depreciation: Parameters!$J$25:$N$25
Name P.F.Dividends: Parameters!$J$28:$N$28
Name P.F.Int.Exp: 'Debt Schedule'!$J$21:$N$21
Name P.F.Inventory: Parameters!$J$36:$N$36
Name P.F.Inventory.Days: Parameters!$J$36:$N$36

Sheet Parameters
A1: Parameters
B2: Company name | G2: LeBronLiBerty Inc.
B3: Starting Year | G3: 2025
B4: Financial Statements Assumptions | G4: {=_xlfn.SEQUENCE(1,3,start.year)} -> 2025 | H4: 2026 | I4: 2027 | J4: {=_xlfn.SEQUENCE(1,5,I4+1)} -> 2028 | K4: 2029 | L4: 2030 | M4: 2031 | N4: 2032
C5: Revenues
D6: Basketballs | G6: 7900 | H6: 8089 | I6: 8232 | J6: =I6*(1+J10) -> 8403.2354 | K6: =J6*(1+K10) -> 8564.9116 | L6: =K6*(1+L10) -> 8736.3852 | M6: =L6*(1+M10) -> 8907.8815 | N6: =M6*(1+N10) -> 9084.4829
D7: Shoes | G7: 8179 | H7: 8105 | I7: 8375 | J7: =I7*(1+J11) -> 8476.6106 | K7: =J7*(1+K11) -> 8669.2219 | L7: =K7*(1+L11) -> 8820.3061 | M7: =L7*(1+M11) -> 8997.3752 | N7: =M7*(1+N11) -> 9166.0886
D8: Apparel | G8: 8173 | H8: 8174 | I8: 8371 | J8: =I8*(1+J12) -> 8472.386 | K8: =J8*(1+K12) -> 8625.7887 | L8: =K8*(1+L12) -> 8756.1148 | M8: =L8*(1+M12) -> 8901.5323 | N8: =M8*(1+N12) -> 9042.6947
C9: Deltas
D10: {=+D6:D8} -> Basketballs | H10: =+H6/G6-1 -> 0.023924051 | I10: =+I6/H6-1 -> 0.017678329 | J10: =AVERAGE(H10:I10) -> 0.02080119 | K10: =AVERAGE(I10:J10) -> 0.019239759 | L10: =AVERAGE(J10:K10) -> 0.020020474 | M10: =AVERAGE(K10:L10) -> 0.019630117 | N10: =AVERAGE(L10:M10) -> 0.019825296
D11: Shoes | H11: =+H7/G7-1 -> -0.0090475608 | I11: =+I7/H7-1 -> 0.03331277 | J11: =AVERAGE(H11:I11) -> 0.012132605 | K11: =AVERAGE(I11:J11) -> 0.022722687 | L11: =AVERAGE(J11:K11) -> 0.017427646 | M11: =AVERAGE(K11:L11) -> 0.020075167 | N11: =AVERAGE(L11:M11) -> 0.018751406
D12: Apparel | H12: =+H8/G8-1 -> 0.00012235409 | I12: =+I8/H8-1 -> 0.024100807 | J12: =AVERAGE(H12:I12) -> 0.012111581 | K12: =AVERAGE(I12:J12) -> 0.018106194 | L12: =AVERAGE(J12:K12) -> 0.015108887 | M12: =AVERAGE(K12:L12) -> 0.016607541 | N12: =AVERAGE(L12:M12) -> 0.015858214
C13: Costs of Goods Sold
D14: {=+D6:D8} -> Basketballs | G14: 0.48 | H14: 0.47 | I14: 0.49 | J14: =AVERAGE(G14:I14) -> 0.48 | K14: =AVERAGE(H14:J14) -> 0.48 | L14: =AVERAGE(I14:K14) -> 0.48333333 | M14: =AVERAGE(J14:L14) -> 0.48111111 | N14: =AVERAGE(K14:M14) -> 0.48148148
D15: Shoes | G15: 0.47 | H15: 0.45 | I15: 0.48 | J15: =AVERAGE(G15:I15) -> 0.46666667 | K15: =AVERAGE(H15:J15) -> 0.46555556 | L15: =AVERAGE(I15:K15) -> 0.47074074 | M15: =AVERAGE(J15:L15) -> 0.46765432 | N15: =AVERAGE(K15:M15) -> 0.46798354
D16: Apparel | G16: 0.5 | H16: 0.5 | I16: 0.49 | J16: =AVERAGE(G16:I16) -> 0.49666667 | K16: =AVERAGE(H16:J16) -> 0.49555556 | L16: =AVERAGE(I16:K16) -> 0.49407407 | M16: =AVERAGE(J16:L16) -> 0.4954321 | N16: =AVERAGE(K16:M16) -> 0.49502058
C19: OpEx
D20: Rent | G20: 0.03 | H20: =+G20 -> 0.03 | I20: =+H20 -> 0.03 | J20: =+I20 -> 0.03 | K20: =+J20 -> 0.03 | L20: =+K20 -> 0.03 | M20: =+L20 -> 0.03 | N20: =+M20 -> 0.03
D21: Elctricity | G21: 0.025 | H21: =+G21 -> 0.025 | I21: =+H21 -> 0.025 | J21: =+I21 -> 0.025 | K21: =+J21 -> 0.025 | L21: =+K21 -> 0.025 | M21: =+L21 -> 0.025 | N21: =+M21 -> 0.025
D22: Phone | G22: 0.028 | H22: =+G22 -> 0.028 | I22: =+H22 -> 0.028 | J22: =+I22 -> 0.028 | K22: =+J22 -> 0.028 | L22: =+K22 -> 0.028 | M22: =+L22 -> 0.028 | N22: =+M22 -> 0.028
D23: Insurance | G23: 0.031 | H23: =+G23 -> 0.031 | I23: =+H23 -> 0.031 | J23: =+I23 -> 0.031 | K23: =+J23 -> 0.031 | L23: =+K23 -> 0.031 | M23: =+L23 -> 0.031 | N23: =+M23 -> 0.031
D24: Payroll | G24: 0.105 | H24: =+G24 -> 0.105 | I24: =+H24 -> 0.105 | J24: =+I24 -> 0.105 | K24: =+J24 -> 0.105 | L24: =+K24 -> 0.105 | M24: =+L24 -> 0.105 | N24: =+M24 -> 0.105
D25: Depreciation | G25: 2500 | H25: =+G25 -> 2500 | I25: =+H25 -> 2500 | J25: =+I25 -> 2500 | K25: =+J25 -> 2500 | L25: =+K25 -> 2500 | M25: =+L25 -> 2500 | N25: =+M25 -> 2500
D26: Amorizarion | G26: 250 | H26: =+G26 -> 250 | I26: =+H26 -> 250 | J26: =+I26 -> 250 | K26: =+J26 -> 250 | L26: =+K26 -> 250 | M26: =+L26 -> 250 | N26: =+M26 -> 250
C27: Tax Rate | G27: 0.21 | H27: =+G27 -> 0.21 | I27: =+H27 -> 0.21 | J27: =+I27 -> 0.21 | K27: =+J27 -> 0.21 | L27: =+K27 -> 0.21 | M27: =+L27 -> 0.21 | N27: =+M27 -> 0.21
C28: Cash Dividends | G28: 350 | H28: 350 | I28: 375 | J28: 2850 | K28: =+J28 -> 2850 | L28: =+K28 -> 2850 | M28: =+L28 -> 2850 | N28: =+M28 -> 2850
C29: Stock Buybacks | G29: 250 | H29: 250 | I29: 250 | J29: 1500 | K29: =+J29 -> 1500 | L29: =+K29 -> 1500 | M29: =+L29 -> 1500 | N29: =+M29 -> 1500
C32: Balance Sheet Assumptions
D33: Starting Cash | G33: 3500
D34: Working Capital Assumptions
E35: Accounts Receivable (Days of Revenues) | G35: 30 | H35: 35 | I35: 31 | J35: =AVERAGE(H35:I35) -> 33 | K35: =AVERAGE(I35:J35) -> 32 | L35: =AVERAGE(J35:K35) -> 32.5 | M35: =AVERAGE(K35:L35) -> 32.25 | N35: =AVERAGE(L35:M35) -> 32.375
E36: Inventory (days of COGS) | G36: 31 | H36: 32 | I36: 31 | J36: =AVERAGE(H36:I36) -> 31.5 | K36: =AVERAGE(I36:J36) -> 31.25 | L36: =AVERAGE(J36:K36) -> 31.375 | M36: =AVERAGE(K36:L36) -> 31.3125 | N36: =AVERAGE(L36:M36) -> 31.34375
E37: Prepaid Expenses (% Revenues) | G37: 0.02 | H37: =+G37 -> 0.02 | I37: =+H37 -> 0.02 | J37: =AVERAGE(H37:I37) -> 0.02 | K37: =AVERAGE(I37:J37) -> 0.02 | L37: =AVERAGE(J37:K37) -> 0.02 | M37: =AVERAGE(K37:L37) -> 0.02 | N37: =AVERAGE(L37:M37) -> 0.02
E38: Accounts Payable (Dats of COGS) | G38: 30 | H38: 30 | I38: 30 | J38: =AVERAGE(H38:I38) -> 30 | K38: =AVERAGE(I38:J38) -> 30 | L38: =AVERAGE(J38:K38) -> 30 | M38: =AVERAGE(K38:L38) -> 30 | N38: =AVERAGE(L38:M38) -> 30
E39: Accrued Liabilities | G39: 0.02 | H39: =+G39 -> 0.02 | I39: =+H39 -> 0.02 | J39: =AVERAGE(H39:I39) -> 0.02 | K39: =AVERAGE(I39:J39) -> 0.02 | L39: =AVERAGE(J39:K39) -> 0.02 | M39: =AVERAGE(K39:L39) -> 0.02 | N39: =AVERAGE(L39:M39) -> 0.02
D41: PP&E
E42: Starting Gross | G42: 5000
E43: Starting AccDep | G43: 1000
E44: Capital Expenditures (CapEx) | H44: 3000 | I44: =+H44 -> 3000 | J44: =+I44 -> 3000 | K44: =+J44 -> 3000 | L44: =+K44 -> 3000 | M44: =+L44 -> 3000 | N44: =+M44 -> 3000
D45: Starting Goodwill | G45: 2000
D46: Starting Intillectual Property | G46: 1500
D47: Stating Treasury Stock | G47: 500
D48: Starting Retained Earnings | G48: =2500-1474.5681-0.000036986300983699 -> 1025.4319

Sheet Financial Statements
A1: ="Financial Statements of "&Comapny.Name -> Financial Statements of LeBronLiBerty Inc.
B2: Income Statement
C3: Revenues | G3: {=_xlfn.ANCHORARRAY(years)} -> 2025 | H3: 2026 | I3: 2027 | J3: {=_xlfn.SEQUENCE(1,5,I3+1)} -> 2028 | K3: 2029 | L3: 2030 | M3: 2031 | N3: 2032
D4: Basketballs | G4: {=P.H.Revenues} -> 7900 | H4: 8089 | I4: 8232 | J4: {=P.F.Revenues} -> 8403.2354 | K4: 8564.9116 | L4: 8736.3852 | M4: 8907.8815 | N4: 9084.4829
D5: Shoes | G5: 8179 | H5: 8105 | I5: 8375 | J5: 8476.6106 | K5: 8669.2219 | L5: 8820.3061 | M5: 8997.3752 | N5: 9166.0886
D6: Apparel | G6: 8173 | H6: 8174 | I6: 8371 | J6: 8472.386 | K6: 8625.7887 | L6: 8756.1148 | M6: 8901.5323 | N6: 9042.6947
C7: Total Revenues | G7: =SUM(G4:G6) -> 24252 | H7: =SUM(H4:H6) -> 24368 | I7: =SUM(I4:I6) -> 24978 | J7: =SUM(J4:J6) -> 25352.232 | K7: =SUM(K4:K6) -> 25859.922 | L7: =SUM(L4:L6) -> 26312.806 | M7: =SUM(M4:M6) -> 26806.789 | N7: =SUM(N4:N6) -> 27293.266
C9: Cost of Goods Sold
D10: {=+D4:D6} -> Basketballs | G10: {=+P.H.Revenues*(P.H.COGS)} -> 3792 | H10: 3801.83 | I10: 4033.68 | J10: {=P.F.Revenues*P.F.COGS} -> 4033.553 | K10: 4111.1576 | L10: 4222.5862 | M10: 4285.6808 | N10: 4374.0103
D11: Shoes | G11: 3844.13 | H11: 3647.25 | I11: 4020 | J11: 3955.7516 | K11: 4036.0044 | L11: 4152.0774 | M11: 4207.6614 | N11: 4289.5786
D12: Apparel | G12: 4086.5 | H12: 4087 | I12: 4101.79 | J12: 4207.9517 | K12: 4274.5575 | L12: 4326.1693 | M12: 4410.1048 | N12: 4476.3199
C13: Total Revenues | G13: =SUM(G10:G12) -> 11722.63 | H13: =SUM(H10:H12) -> 11536.08 | I13: =SUM(I10:I12) -> 12155.47 | J13: =SUM(J10:J12) -> 12197.256 | K13: =SUM(K10:K12) -> 12421.72 | L13: =SUM(L10:L12) -> 12700.833 | M13: =SUM(M10:M12) -> 12903.447 | N13: =SUM(N10:N12) -> 13139.909
C15: Gross Margin | G15: {=+H.Revenues-H.COGS} -> 12529.37 | H15: 12831.92 | I15: 12822.53 | J15: {=f.revenues-F.COGS} -> 13154.976 | K15: 13438.203 | L15: 13611.973 | M15: 13903.342 | N15: 14153.357
D16: % of Sales | G16: {=+H.Margin/H.Revenues} -> 0.51663244 | H16: 0.52658897 | I16: 0.51335295 | J16: {=+F.Margin/f.revenues} -> 0.51888827 | K16: 0.51965364 | L16: 0.51731363 | M16: 0.51865003 | N16: 0.51856591
C18: OpEx
D19: Rent | G19: {=+P.H.OpEx*H.Revenues} -> 727.56 | H19: 731.04 | I19: 749.34 | J19: {=P.F.OpEx*f.revenues} -> 760.56696 | K19: 775.79767 | L19: 789.38418 | M19: 804.20367 | N19: 818.79799
D20: Elctricity | G20: 606.3 | H20: 609.2 | I20: 624.45 | J20: 633.8058 | K20: 646.49806 | L20: 657.82015 | M20: 670.16972 | N20: 682.33165
D21: Phone | G21: 679.056 | H21: 682.304 | I21: 699.384 | J21: 709.8625 | K21: 724.07782 | L21: 736.75857 | M21: 750.59009 | N21: 764.21145
D22: Insurance | G22: 751.812 | H22: 755.408 | I22: 774.318 | J22: 785.91919 | K22: 801.65759 | L22: 815.69699 | M22: 831.01046 | N22: 846.09125
D23: Payroll | G23: 2546.46 | H23: 2558.64 | I23: 2622.69 | J23: 2661.9844 | K23: 2715.2918 | L23: 2762.8446 | M23: 2814.7128 | N23: 2865.7929
D24: Depreciation | G24: {=+P.H.Depreciation} -> 2500 | H24: 2500 | I24: 2500 | J24: {=P.F.Depreciation} -> 2500 | K24: 2500 | L24: 2500 | M24: 2500 | N24: 2500
D25: Amorizarion | G25: {=+P.H.Amorization} -> 250 | H25: 250 | I25: 250 | J25: {=P.F.Amorization} -> 250 | K25: 250 | L25: 250 | M25: 250 | N25: 250
C26: Net Operating Expenses | G26: =SUM(G19:G25) -> 8061.188 | H26: =SUM(H19:H25) -> 8086.592 | I26: =SUM(I19:I25) -> 8220.182 | J26: =SUM(J19:J25) -> 8302.1388 | K26: =SUM(K19:K25) -> 8413.323 | L26: =SUM(L19:L25) -> 8512.5045 | M26: =SUM(M19:M25) -> 8620.6868 | N26: =SUM(N19:N25) -> 8727.2253
C28: Earnings Before Interest & Taxes (EBIT) | G28: {=+H.Margin-G26:I26} -> 4468.182 | H28: 4745.328 | I28: 4602.348 | J28: {=F.Margin-F.OpEx} -> 4852.8369 | K28: 5024.8798 | L28: 5099.4686 | M28: 5282.6552 | N28: 5426.1321
C30: Interest Expense | G30: {=D.H.Int.Expense} -> 355.625 | H30: 367 | I30: 348.375 | J30: {=D.F.Int.Exp} -> 331.125 | K30: 316.75 | L30: 302.375 | M30: 288 | N30: 273.625
C32: Earnings Befor Taxes(EBT) | G32: {=+_xlfn.ANCHORARRAY(G28)-G30:I30} -> 4112.557 | H32: 4378.328 | I32: 4253.973 | J32: {=+_xlfn.ANCHORARRAY(J28)-_xlfn.ANCHORARRAY(J30)} -> 4521.7119 | K32: 4708.1298 | L32: 4797.0936 | M32: 4994.6552 | N32: 5152.5071
C34: Income Tax Expense | G34: {=+_xlfn.ANCHORARRAY(G32)*Tax.Rate} -> 863.63697 | H34: 919.44888 | I34: 893.33433 | J34: {=_xlfn.ANCHORARRAY(J32)*P.F.Tax} -> 949.55949 | K34: 988.70725 | L34: 1007.3897 | M34: 1048.8776 | N34: 1082.0265
C36: Net Income | G36: {=+_xlfn.ANCHORARRAY(G32)-_xlfn.ANCHORARRAY(G34)} -> 3248.92 | H36: 3458.8791 | I36: 3360.6387 | J36: {=_xlfn.ANCHORARRAY(J32)-_xlfn.ANCHORARRAY(J34)} -> 3572.1524 | K36: 3719.4225 | L36: 3789.704 | M36: 3945.7776 | N36: 4070.4806
C37: Less: Cash Dividends | G37: {=-P.H.Dividends} -> -350 | H37: -350 | I37: -375 | J37: {=-P.F.Dividends} -> -2850 | K37: -2850 | L37: -2850 | M37: -2850 | N37: -2850
C38: Change in Retained Earnings | G38: {=+H.Net.Income+_xlfn.ANCHORARRAY(G37)} -> 2898.92 | H38: 3108.8791 | I38: 2985.6387 | J38: {=_xlfn.ANCHORARRAY(J36)+_xlfn.ANCHORARRAY(J37)} -> 722.15238 | K38: 869.42251 | L38: 939.70397 | M38: 1095.7776 | N38: 1220.4806
B41: Balance Sheet | G41: {=_xlfn.ANCHORARRAY(years)} -> 2025 | H41: 2026 | I41: 2027 | J41: {=_xlfn.SEQUENCE(1,5,I41+1)} -> 2028 | K41: 2029 | L41: 2030 | M41: 2031 | N41: 2032
C42: Assets
D43: Short Term Assets
E44: Cash | G44: {=+H.Cash} -> 3500 | H44: 5484.4421 | I44: 7515.2278 | J44: {=+F.Cash} -> 5999.8567 | K44: 4901.8131 | L44: 3760.4618 | M44: 2832.0617 | N44: 1998.2367
E45: Accounts Receivable | G45: {=+H.Revenues*(P.H.Accts.Rec.Days/365)} -> 1993.3151 | H45: 2336.6575 | I45: 2121.4192 | J45: {=+f.revenues*(P.F.Accts.Rec.Days/365)} -> 2292.1196 | K45: 2267.1713 | L45: 2342.9211 | M45: 2368.5451 | N45: 2420.8753
E46: Inventory | G46: {=+H.COGS*(P.H.Inventory.Days/365)} -> 995.62063 | H46: 1011.3824 | I46: 1032.3824 | J46: {=+F.COGS*(P.F.Inventory.Days/365)} -> 1052.6399 | K46: 1063.5034 | L46: 1091.7497 | M46: 1106.9567 | N46: 1128.3672
E47: Prepaid Expenses | G47: {=+H.Revenues*P.H.Prepaids} -> 485.04 | H47: 487.36 | I47: 499.56 | J47: {=+f.revenues*P.F.Prepaids} -> 507.04464 | K47: 517.19845 | L47: 526.25612 | M47: 536.13578 | N47: 545.86532
D48: Total Shot Term Assets | G48: =SUM(G44:G47) -> 6973.9757 | H48: =SUM(H44:H47) -> 9319.8419 | I48: =SUM(I44:I47) -> 11168.589 | J48: =SUM(J44:J47) -> 9851.6609 | K48: =SUM(K44:K47) -> 8749.6862 | L48: =SUM(L44:L47) -> 7721.3887 | M48: =SUM(M44:M47) -> 6843.6992 | N48: =SUM(N44:N47) -> 6093.3446
D50: Long Term Assets
E51: Property, Plant, Equipment
F52: Gross PP&E | G52: =+Start.Gross -> 5000 | H52: =+G52+Parameters!H44 -> 8000 | I52: =+H52+Parameters!I44 -> 11000 | J52: =+I52+Parameters!J44 -> 14000 | K52: =+J52+Parameters!K44 -> 17000 | L52: =+K52+Parameters!L44 -> 20000 | M52: =+L52+Parameters!M44 -> 23000 | N52: =+M52+Parameters!N44 -> 26000
F53: Accumulated Depreciation | G53: =-Start.AccDep -> -1000 | H53: =+G53-H24 -> -3500 | I53: =+H53-I24 -> -6000 | J53: =+I53-J24 -> -8500 | K53: =+J53-K24 -> -11000 | L53: =+K53-L24 -> -13500 | M53: =+L53-M24 -> -16000 | N53: =+M53-N24 -> -18500
E54: Net PP&E | G54: =SUM(G52:G53) -> 4000 | H54: =SUM(H52:H53) -> 4500 | I54: =SUM(I52:I53) -> 5000 | J54: =SUM(J52:J53) -> 5500 | K54: =SUM(K52:K53) -> 6000 | L54: =SUM(L52:L53) -> 6500 | M54: =SUM(M52:M53) -> 7000 | N54: =SUM(N52:N53) -> 7500
E55: Goodwill | G55: =Start.Goodwill -> 2000 | H55: =G55-H25 -> 1750 | I55: =H55-I25 -> 1500 | J55: =I55-J25 -> 1250 | K55: =J55-K25 -> 1000 | L55: =K55-L25 -> 750 | M55: =L55-M25 -> 500 | N55: =M55-N25 -> 250
E56: Intillectual Property | G56: =Start.IP -> 1500 | H56: =+G56 -> 1500 | I56: =+H56 -> 1500 | J56: =+I56 -> 1500 | K56: =+J56 -> 1500 | L56: =+K56 -> 1500 | M56: =+L56 -> 1500 | N56: =+M56 -> 1500
D57: Total Long Term Assets | G57: =SUM(G54:G56) -> 7500 | H57: =SUM(H54:H56) -> 7750 | I57: =SUM(I54:I56) -> 8000 | J57: =SUM(J54:J56) -> 8250 | K57: =SUM(K54:K56) -> 8500 | L57: =SUM(L54:L56) -> 8750 | M57: =SUM(M54:M56) -> 9000 | N57: =SUM(N54:N56) -> 9250
C58: Total Assets | G58: {=H.ST.Assets+H.LT.Assets} -> 14473.976 | H58: 17069.842 | I58: 19168.589 | J58: =+J57+J48 -> 18101.661 | K58: =+K57+K48 -> 17249.686 | L58: =+L57+L48 -> 16471.389 | M58: =+M57+M48 -> 15843.699 | N58: =+N57+N48 -> 15343.345
C60: Liabilities & Equity
D61: Liabilities
E62: Short-Term Liabilities
F63: Accounts Payable | G63: {=+H.COGS*(P.H.Accounts.Payable/365)} -> 963.50384 | H63: 948.17096 | I63: 999.07973 | J63: {=+F.COGS*(P.F.Accounts.Payable/365)} -> 1002.5142 | K63: 1020.9632 | L63: 1043.9041 | M63: 1060.5573 | N63: 1079.9925
F64: Accrued Liabilities | G64: {=H.Revenues*P.H.Accruds} -> 485.04 | H64: 487.36 | I64: 499.56 | J64: {=f.revenues*P.F.Accruds} -> 507.04464 | K64: 517.19845 | L64: 526.25612 | M64: 536.13578 | N64: 545.86532
F65: Current Potion of Notes Payable | G65: {=D.H.STDebt} -> 250 | H65: 700 | I65: 300 | J65: {=D.F.STDebt} -> 250 | K65: 250 | L65: 250 | M65: 250 | N65: 250
E66: Total Short Term Liabilities | G66: =SUM(G63:G65) -> 1698.5438 | H66: =SUM(H63:H65) -> 2135.531 | I66: =SUM(I63:I65) -> 1798.6397 | J66: =SUM(J63:J65) -> 1759.5589 | K66: =SUM(K63:K65) -> 1788.1617 | L66: =SUM(L63:L65) -> 1820.1602 | M66: =SUM(M63:M65) -> 1846.6931 | N66: =SUM(N63:N65) -> 1875.8578
E68: Long Term Liabilities
F69: Notes Payable | G69: {=+D.H.LTDebt} -> 6250 | H69: 5550 | I69: 5250 | J69: {=D.F.LTDEBT} -> 5000 | K69: 4750 | L69: 4500 | M69: 4250 | N69: 4000
F70: Capitalized Lease | G70: 1000 | H70: =+G70 -> 1000 | I70: =+H70 -> 1000 | J70: =+I70 -> 1000 | K70: =+J70 -> 1000 | L70: =+K70 -> 1000 | M70: =+L70 -> 1000 | N70: =+M70 -> 1000
E71: Total Long Term Liabilities | G71: =SUM(G69:G70) -> 7250 | H71: =SUM(H69:H70) -> 6550 | I71: =SUM(I69:I70) -> 6250 | J71: =SUM(J69:J70) -> 6000 | K71: =SUM(K69:K70) -> 5750 | L71: =SUM(L69:L70) -> 5500 | M71: =SUM(M69:M70) -> 5250 | N71: =SUM(N69:N70) -> 5000
D72: Total Liabilities | G72: {=+G66:I66+G71:I71} -> 8948.5438 | H72: 8685.531 | I72: 8048.6397 | J72: {=+J66:N66+J71:N71} -> 7759.5589 | K72: 7538.1617 | L72: 7320.1602 | M72: 7096.6931 | N72: 6875.8578
D74: Shareholdes Equity
E75: Prefered Stock | G75: 1500 | H75: =+G75 -> 1500 | I75: =+H75 -> 1500 | J75: =+I75 -> 1500 | K75: =+J75 -> 1500 | L75: =+K75 -> 1500 | M75: =+L75 -> 1500 | N75: =+M75 -> 1500
E76: Common Stock | G76: 3500 | H76: 3500 | I76: 3500 | J76: 3500 | K76: 3500 | L76: 3500 | M76: 3500 | N76: 3500
E77: Treasury Shares | G77: =-Start.Treasury -> -500 | H77: =+G77-Parameters!H29 -> -750 | I77: =+H77-Parameters!I29 -> -1000 | J77: =+I77-Parameters!J29 -> -2500 | K77: =+J77-Parameters!K29 -> -4000 | L77: =+K77-Parameters!L29 -> -5500 | M77: =+L77-Parameters!M29 -> -7000 | N77: =+M77-Parameters!N29 -> -8500
E78: Retained Earnings | G78: =Start.Retained.earnings -> 1025.4319 | H78: =G78+H38 -> 4134.311 | I78: =H78+I38 -> 7119.9497 | J78: =I78+J38 -> 7842.102 | K78: =J78+K38 -> 8711.5245 | L78: =K78+L38 -> 9651.2285 | M78: =L78+M38 -> 10747.006 | N78: =M78+N38 -> 11967.487
D79: Total Equity | G79: =SUM(G75:G78) -> 5525.4319 | H79: =SUM(H75:H78) -> 8384.311 | I79: =SUM(I75:I78) -> 11119.95 | J79: =SUM(J75:J78) -> 10342.102 | K79: =SUM(K75:K78) -> 9711.5245 | L79: =SUM(L75:L78) -> 9151.2285 | M79: =SUM(M75:M78) -> 8747.0061 | N79: =SUM(N75:N78) -> 8467.4867
C80: Total Liabilities & Equity | G80: {=+_xlfn.ANCHORARRAY(G72)+G79:I79} -> 14473.976 | H80: 17069.842 | I80: 19168.589 | J80: {=+_xlfn.ANCHORARRAY(J72)+F.Equity} -> 18101.661 | K80: 17249.686 | L80: 16471.389 | M80: 15843.699 | N80: 15343.345
C82: Checksum | G82: {=H.Assets-H.Capital} -> 0 | H82: 0 | I82: 0 | J82: {=F.Assets-f.Capital} -> 0 | K82: 0 | L82: 0 | M82: 0 | N82: 0
B85: Statement of Cash Flow | G85: {=_xlfn.ANCHORARRAY(years)} -> 2025 | H85: 2026 | I85: 2027 | J85: {=_xlfn.SEQUENCE(1,5,I85+1)} -> 2028 | K85: 2029 | L85: 2030 | M85: 2031 | N85: 2032
C86: Cash from Opperations
D87: Net Income | G87: {=+H.Net.Income} -> 3248.92 | H87: 3458.8791 | I87: 3360.6387 | J87: {=+F.Net.Income} -> 3572.1524 | K87: 3719.4225 | L87: 3789.704 | M87: 3945.7776 | N87: 4070.4806
D88: Add Back:
E89: Depeciation Expense | H89: {=_xlfn.TAKE(P.H.Depreciation,1,-2)} -> 2500 | I89: 2500 | J89: {=_xlfn.TAKE(P.F.Depreciation,1,-5)} -> 2500 | K89: 2500 | L89: 2500 | M89: 2500 | N89: 2500
E90: Amortization Expense | H90: {=_xlfn.TAKE(P.H.Amorization,1,-2)} -> 250 | I90: 250 | J90: {=+_xlfn.TAKE(P.F.Amorization,1,-5)} -> 250 | K90: 250 | L90: 250 | M90: 250 | N90: 250
D91: Change in Working Capital
E92: Accounts Receivable | H92: =+G45-H45 -> -343.34247 | I92: =+H45-I45 -> 215.23836 | J92: =+I45-J45 -> -170.70043 | K92: =+J45-K45 -> 24.948339 | L92: =+K45-L45 -> -75.74982 | M92: =+L45-M45 -> -25.623965 | N92: =+M45-N45 -> -52.330271
E93: Inentory | H93: =+G46-H46 -> -15.761726 | I93: =+H46-I46 -> -21.000027 | J93: =+I46-J46 -> -20.257545 | K93: =+J46-K46 -> -10.863455 | L93: =+K46-L46 -> -28.246293 | M93: =+L46-M46 -> -15.206989 | N93: =+M46-N46 -> -21.410502
E94: Prepaid Expenses | H94: =+G47-H47 -> -2.32 | I94: =+H47-I47 -> -12.2 | J94: =+I47-J47 -> -7.48464 | K94: =+J47-K47 -> -10.153805 | L94: =+K47-L47 -> -9.0576759 | M94: =+L47-M47 -> -9.8796582 | N94: =+M47-N47 -> -9.7295445
E95: Accounts Payable | H95: =+H63-G63 -> -15.332877 | I95: =+I63-H63 -> 50.908767 | J95: =+J63-I63 -> 3.434492 | K95: =+K63-J63 -> 18.449031 | L95: =+L63-K63 -> 22.940825 | M95: =+M63-L63 -> 16.653211 | N95: =+N63-M63 -> 19.435219
E96: Accrued Liabilities | H96: =+H64-G64 -> 2.32 | I96: =+I64-H64 -> 12.2 | J96: =+J64-I64 -> 7.48464 | K96: =+K64-J64 -> 10.153805 | L96: =+L64-K64 -> 9.0576759 | M96: =+M64-L64 -> 9.8796582 | N96: =+N64-M64 -> 9.7295445
D97: Net Cash from Operations | H97: =SUM(H87:H96) -> 5834.4421 | I97: =SUM(I87:I96) -> 6355.7858 | J97: =SUM(J87:J96) -> 6134.6289 | K97: =SUM(K87:K96) -> 6501.9564 | L97: =SUM(L87:L96) -> 6458.6487 | M97: =SUM(M87:M96) -> 6671.5999 | N97: =SUM(N87:N96) -> 6766.175
D99: Cash From Investments
E100: CapEx | H100: {=_xlfn.TAKE(-P.H.CapEx,1,-2)} -> -3000 | I100: -3000 | J100: {=+_xlfn.TAKE(-P.F.CapEx,1,-5)} -> -3000 | K100: -3000 | L100: -3000 | M100: -3000 | N100: -3000
E101: Gain/(Loss) on Disposals
D102: Net Cash from Investments | H102: =SUM(H100:H101) -> -3000 | I102: =SUM(I100:I101) -> -3000 | J102: =SUM(J100:J101) -> -3000 | K102: =SUM(K100:K101) -> -3000 | L102: =SUM(L100:L101) -> -3000 | M102: =SUM(M100:M101) -> -3000 | N102: =SUM(N100:N101) -> -3000
D104: Cash from Financing
E105: Borrowing/(repayment) of Debt | H105: =+'Debt Schedule'!H8-'Debt Schedule'!G8 -> -250 | I105: =+'Debt Schedule'!I8-'Debt Schedule'!H8 -> -700 | J105: =+'Debt Schedule'!J8-'Debt Schedule'!I8 -> -300 | K105: =+'Debt Schedule'!K8-'Debt Schedule'!J8 -> -250 | L105: =+'Debt Schedule'!L8-'Debt Schedule'!K8 -> -250 | M105: =+'Debt Schedule'!M8-'Debt Schedule'!L8 -> -250 | N105: =+'Debt Schedule'!N8-'Debt Schedule'!M8 -> -250
E106: Issuance of Shares | H106: =+H76-G76 -> 0 | I106: =+I76-H76 -> 0 | J106: =+J76-I76 -> 0 | K106: =+K76-J76 -> 0 | L106: =+L76-K76 -> 0 | M106: =+M76-L76 -> 0 | N106: =+N76-M76 -> 0
E107: Stock Repurchase | H107: {=-_xlfn.TAKE(P.H.Buybacks,1,-2)} -> -250 | I107: -250 | J107: {=-_xlfn.TAKE(P.F.Buybacks,1,-5)} -> -1500 | K107: -1500 | L107: -1500 | M107: -1500 | N107: -1500
E108: Cash Dividends | H108: {=-_xlfn.TAKE(P.H.Dividends,1,-2)} -> -350 | I108: -375 | J108: {=-_xlfn.TAKE(P.F.Dividends,1,-5)} -> -2850 | K108: -2850 | L108: -2850 | M108: -2850 | N108: -2850
D109: Net Cash from Financing | H109: =SUM(H105:H108) -> -850 | I109: =SUM(I105:I108) -> -1325 | J109: =SUM(J105:J108) -> -4650 | K109: =SUM(K105:K108) -> -4600 | L109: =SUM(L105:L108) -> -4600 | M109: =SUM(M105:M108) -> -4600 | N109: =SUM(N105:N108) -> -4600
C111: Net Change in Cash | H111: {=H.Cash.Financing+H.Cash.Investment+H.Cash.Ops} -> 1984.4421 | I111: 2030.7858 | J111: {=F.Cash.Financing+F.Cash.Investment+F.Cash.Ops} -> -1515.3711 | K111: -1098.0436 | L111: -1141.3513 | M111: -928.40013 | N111: -833.82495
C112: Cash @ Beginning of Year | H112: =+G113 -> 3500 | I112: =+H113 -> 5484.4421 | J112: =+I113 -> 7515.2278 | K112: =+J113 -> 5999.8567 | L112: =+K113 -> 4901.8131 | M112: =+L113 -> 3760.4618 | N112: =+M113 -> 2832.0617
C113: Cash @ End of Year | G113: =+starting.cash -> 3500 | H113: =SUM(H111:H112) -> 5484.4421 | I113: =SUM(I111:I112) -> 7515.2278 | J113: =SUM(J111:J112) -> 5999.8567 | K113: =SUM(K111:K112) -> 4901.8131 | L113: =SUM(L111:L112) -> 3760.4618 | M113: =SUM(M111:M112) -> 2832.0617 | N113: =SUM(N111:N112) -> 1998.2367

Sheet DCF
A1: ="Discount Cash Flow Analysis for "&Comapny.Name -> Discount Cash Flow Analysis for LeBronLiBerty Inc.
B2: Weighted Average Cost of Capital (WACC)
C3: Assumptions | G3: #VALUE!
D4: Share Price | G4: {=+_FV(G3,"Price")} -> 12.43
D5: Shares Oustanding(mm of shares) | G5: {=_FV(G3,"Shares outstanding",TRUE)/1000000} -> 3987.596
D6: Market Cap ($mm) | G6: {=+_FV(G3,"Market cap",TRUE)/1000000} -> 49565.818
C8: Capital Costs | G8: Ammount | H8: Weight | I8: Cost
D9: Debt | G9: {=_xlfn.TAKE(D.H.Total.Debt,1,-1)} -> 5550 | H9: {=+G9:G11/G12} -> 0.33293442 | I9: {=_xlfn.LET( _xlpm.raw_interest,_xlfn.TAKE(D.H.Int.Expense,1,-1)/G9, _xlpm.tax_shield,100%-Tax.Rate, _xlpm.raw_interest*_xlpm.tax_shield )} -> 0.049588514 | J9: 0.049588514 | K9: 0.049588514
D10: Prefered Stock | G10: {=_xlfn.TAKE(H.Pref,1,-1)} -> 1500 | H10: 0.089982275 | I10: 0.0739
D11: Common Stock | G11: {=_xlfn.TAKE(H.Equity,1,-1)-G10} -> 9619.9497 | H11: 0.57708331 | I11: 0.1171
E12: Total Capital | G12: =SUM(G9:G11) -> 16669.95
C13: Weighted Average Cost of Capital | G13: =SUMPRODUCT(_xlfn.ANCHORARRAY(H9),I9:I11) -> 0.090735868
B15: Free Cash Flow Build up | G15: {=_xlfn.ANCHORARRAY(forecast.years)} -> 2028 | H15: 2029 | I15: 2030 | J15: 2031 | K15: 2032
C16: EBITDA | G16: {=+_xlfn.ANCHORARRAY(G18)-_xlfn.ANCHORARRAY(G17)} -> 7602.8369 | H16: 7774.8798 | I16: 7849.4686 | J16: 8032.6552 | K16: 8176.1321
D17: Less: Depreciation & Amortization | G17: {=-P.F.Depreciation-P.F.Amorization} -> -2750 | H17: -2750 | I17: -2750 | J17: -2750 | K17: -2750
C18: EBIT | G18: {=F.EBIT} -> 4852.8369 | H18: 5024.8798 | I18: 5099.4686 | J18: 5282.6552 | K18: 5426.1321
D19: Less:Income Taxes | G19: {=-_xlfn.ANCHORARRAY(G18)*tax.Rate.} -> -1019.0957 | H19: -1055.2247 | I19: -1070.8884 | J19: -1109.3576 | K19: -1139.4877
C20: EBIAT(NOPAT- Net) | G20: =SUM(G18:G19) -> 3833.7411 | H20: =SUM(H18:H19) -> 3969.655 | I20: =SUM(I18:I19) -> 4028.5802 | J20: =SUM(J18:J19) -> 4173.2976 | K20: =SUM(K18:K19) -> 4286.6444
D21: Adjustments
E22: Add Back: Dep & Amort | G22: {=-_xlfn.ANCHORARRAY(G17)} -> 2750 | H22: 2750 | I22: 2750 | J22: 2750 | K22: 2750
E23: Change in Working Capital | G23: =SUM('Financial Statements'!J92:J96) -> -187.52348 | H23: =SUM('Financial Statements'!K92:K96) -> 32.533914 | I23: =SUM('Financial Statements'!L92:L96) -> -81.055288 | J23: =SUM('Financial Statements'!M92:M96) -> -24.177743 | K23: =SUM('Financial Statements'!N92:N96) -> -54.305554
D24: Unlevered Cash From Operations | G24: {=+G20:K20+_xlfn.ANCHORARRAY(G22)+G23:K23} -> 6396.2176 | H24: 6752.1889 | I24: 6697.5249 | J24: 6899.1199 | K24: 6982.3388
E25: Less:CapEx | G25: {=-P.F.CapEx} -> -3000 | H25: -3000 | I25: -3000 | J25: -3000 | K25: -3000
D26: Unlevered Free Cash Flow | G26: {=_xlfn.ANCHORARRAY(G24)+_xlfn.ANCHORARRAY(G25)} -> 3396.2176 | H26: 3752.1889 | I26: 3697.5249 | J26: 3899.1199 | K26: 3982.3388
E27: Discount factor | G27: =1/(1+WACC)^G101 -> 0.91681224 | H27: =1/(1+WACC)^H101 -> 0.84054469 | I27: =1/(1+WACC)^I101 -> 0.77062167 | J27: =1/(1+WACC)^J101 -> 0.70651538 | K27: =1/(1+WACC)^K101 -> 0.64774195
D28: NPV or FCF | G28: =SUMPRODUCT(unlev.FCF,Discount) -> 14451.285
A30: Terminal Value Estimations
B31: Perpituity Approach
C32: Unlevered FCF in Year 5 | G32: {=_xlfn.TAKE(unlev.FCF,1,-1)} -> 3982.3388
D33: Long Term Growth Rate | G33: 0.03
C34: Estimated FCF Time T+1 | G34: =+G32*(1+G33) -> 4101.809
C35: Estimated Terminal Enterprise Value | G35: =+G34/(WACC-G33) -> 67535.199
B37: Exit EBITDA Multiple Approach
C38: Terminal EBITDA | G38: =Term.Ebitda -> 8176.1321
C39: Expected Market Multiple | G39: 9
D40: EBITDA Terminal Enterprise Value | G40: =+G38*G39 -> 73585.189
B42: Capital Stack
C43: Cash | G43: {=_xlfn.TAKE(F.Cash,1,-1)} -> 1998.2367
C44: Debt | G44: {=_xlfn.TAKE(-D.F.Total.Debt,1,-1)} -> -4250
C45: Prefered Shares | G45: {=_xlfn.TAKE(-F.Pref,1,-1)} -> -1500
B46: Net Debt | G46: =SUM(G43:G45) -> -3751.7633
B48: Fair Value Per Share | H48: Approach
C49: Valuation Mathodology | H49: Perpetuity | I49: EBITDA Mult
D50: Terminal Value | H50: =+EV.Perp -> 67535.199 | I50: =+EV.Mult -> 73585.189
E51: Discount Factor | H51: {=_xlfn.TAKE(Discount,1,-1)} -> 0.64774195 | I51: =+H51 -> 0.64774195
D52: Discounted TV | H52: =+H50*H51 -> 43745.382 | I52: =+I50*I51 -> 47664.214
D53: Net Present Value FCF | H53: =NPV.FCF -> 14451.285 | I53: =NPV.FCF -> 14451.285
C54: Enterprise Value | H54: {=+H52:I52+H53:I53} -> 58196.667 | I54: 62115.499
C55: Less:Net Debt | H55: =+terminal.Debt -> -3751.7633 | I55: =+terminal.Debt -> -3751.7633
D56: Net Equity Value (aka net residual value) | H56: {=+_xlfn.ANCHORARRAY(H54)+H55:I55} -> 54444.904 | I56: 58363.736
D57: Total Diluted Shaes Outstanding | H57: =shares.outstanding -> 3987.596 | I57: =+H57 -> 3987.596
E58: Equity Value per Share | H58: {=+_xlfn.ANCHORARRAY(H56)/H57:I57} -> 13.653566 | I58: 14.636321
E59: Market premium/ Discount to Estimate | H59: =+H58/share.price-1 -> 0.098436498 | I59: =+I58/share.price-1 -> 0.17749969
C61: Golden Flash Hybrid Inference Valuation
C62: Model Weights (based on proprietary analysis) | H62: 0.439 | I62: 0.561
C64: GFHIVM Valuation | H64: =+SUMPRODUCT(H62:I62,_xlfn.ANCHORARRAY(H58)) -> 14.204892
H70: Equity Value Per Share
I71: Long Term Growth
H72: =price.perp -> 13.653566 | I72: {=_xlfn.SEQUENCE(1,5,2%,0.25%)} -> 0.02 | J72: 0.0225 | K72: 0.025 | L72: 0.0275 | M72: 0.03
G73: WACC | H73: {=_xlfn.SEQUENCE(5,1,7.5%,1.5%)} -> 0.075 | I73: 15.740861 | J73: 16.388319 | K73: 17.100522 | L73: 17.887694 | M73: 18.762329
H74: 0.09 | I74: 12.148242 | J74: 12.522576 | K74: 12.925705 | L74: 13.361084 | M74: 13.832745
H75: 0.105 | I75: 9.8242375 | J75: 10.063043 | K75: 10.316775 | L75: 10.586876 | M75: 10.874984
H76: 0.12 | I76: 8.1979381 | J76: 8.3606767 | K76: 8.5319804 | L76: 8.7125437 | M76: 8.9031384
H77: 0.135 | I77: 6.996302 | J77: 7.1125895 | K77: 7.2341629 | L77: 7.3613908 | M77: 7.4946772
H79: Equity Value Per Share
I80: EBITDA Multiple
H81: =price.mult -> 14.636321 | I81: {=_xlfn.SEQUENCE(1,5,8,1)} -> 8 | J81: 9 | K81: 10 | L81: 11 | M81: 12
G82: WACC | H82: {=_xlfn.SEQUENCE(5,1,7.5%,1.5%)} -> 0.075 | I82: 14.265638 | J82: 15.693856 | K82: 17.122073 | L82: 18.550291 | M82: 19.978509
H83: 0.09 | I83: 13.351208 | J83: 14.683822 | K83: 16.016435 | L83: 17.349049 | M83: 18.681663
H84: 0.105 | I84: 12.50654 | J84: 13.751127 | K84: 14.995715 | L84: 16.240302 | M84: 17.484889
H85: 0.12 | I85: 11.725391 | J85: 12.888838 | K85: 14.052286 | L85: 15.215733 | M85: 16.37918
H86: 0.135 | I86: 11.002153 | J86: 12.090726 | K86: 13.179299 | L86: 14.267871 | M86: 15.356444
H88: Equity Value Per Share
G89: EBITDA % of Forecast | I89: EBITDA Multiple
H90: =price.mult -> 14.636321 | I90: {=_xlfn.SEQUENCE(1,5,2%,0.25%)} -> 0.02 | J90: 0.0225 | K90: 0.025 | L90: 0.0275 | M90: 0.03
G91: {=_xlfn.SEQUENCE(5,1,70%,15%)} -> 0.7 | H91: {=_xlfn.ANCHORARRAY(G91)*_xlfn.TAKE(F.EBITDA,1,-1)} -> 5723.2925 | I91: 2.7017949 | J91: 2.7041191 | K91: 2.7064433 | L91: 2.7087675 | M91: 2.7110917
G92: 0.85 | H92: 6949.7123 | I92: 2.7057792 | J92: 2.7086015 | K92: 2.7114238 | L92: 2.714246 | M92: 2.7170683
G93: 1 | H93: 8176.1321 | I93: 2.7097636 | J93: 2.7130839 | K93: 2.7164042 | L93: 2.7197245 | M93: 2.7230449
G94: 1.15 | H94: 9402.5519 | I94: 2.713748 | J94: 2.7175663 | K94: 2.7213847 | L94: 2.7252031 | M94: 2.7290214
G95: 1.3 | H95: 10628.972 | I95: 2.7177324 | J95: 2.7220488 | K95: 2.7263652 | L95: 2.7306816 | M95: 2.734998
G101: {=_xlfn.SEQUENCE(1,5,1)} -> 1 | H101: 2 | I101: 3 | J101: 4 | K101: 5
E103: Football Field Calculations | H103: Low | I103: Difference | J103: High | K103: GFHIV Valuation
G104: DCF Value- Multiplier 8x-12x | H104: =MIN(Table.mult) -> 11.002153 | I104: =J104-H104 -> 8.9763557 | J104: =MAX(Table.mult) -> 19.978509 | K104: =GFHIVM.Valuation -> 14.204892
G105: DCF Value- Growth Rate 2%-3% | H105: =MIN(Table.perp) -> 6.996302 | I105: =J105-H105 -> 11.766027 | J105: =MAX(Table.perp) -> 18.762329 | K105: =GFHIVM.Valuation -> 14.204892
G106: 52 Week Market high/low | H106: {=_FV(Stock,"52 week low",TRUE)} -> 11.11 | I106: =J106-H106 -> 6.67 | J106: {=_FV(Stock,"52 week high",TRUE)} -> 17.78 | K106: =GFHIVM.Valuation -> 14.204892

Sheet Football Field
A1: DCF Football Field and Scenarios for Lebron Liberty v1
B3: Equity Value Per Share
C4: Long Term Growth
B5: =price.perp -> 13.653566 | C5: {=_xlfn.SEQUENCE(1,5,2%,0.25%)} -> 0.02 | D5: 0.0225 | E5: 0.025 | F5: 0.0275 | G5: 0.03
A6: WACC | B6: {=_xlfn.SEQUENCE(5,1,7.5%,1.5%)} -> 0.075
B7: 0.09
B8: 0.105
B9: 0.12
B10: 0.135

Sheet Debt Schedule
A1: Debt Schedule
C2: Debt Table | G2: 2025 | H2: 2026 | I2: 2027 | J2: {=_xlfn.SEQUENCE(1,5,I2+1)} -> 2028 | K2: 2029 | L2: 2030 | M2: 2031 | N2: 2032
C3: Hunington Revolver | G3: 750 | H3: 750 | I3: 750 | J3: 750 | K3: =+J3 -> 750 | L3: =+K3 -> 750 | M3: =+L3 -> 750 | N3: =+M3 -> 750 | O3: =+N3 -> 750
C4: PNC Term Loan | G4: 3250 | H4: 3000 | I4: 2800 | J4: 2500 | K4: =+J4-250 -> 2250 | L4: =+K4-250 -> 2000 | M4: =+L4-250 -> 1750 | N4: =+M4-250 -> 1500 | O4: =+N4-250 -> 1250
C5: Key Bank Term Loan | G5: 2500 | H5: 2500 | I5: 2000 | J5: 2000 | K5: =+J5 -> 2000 | L5: =+K5 -> 2000 | M5: =+L5 -> 2000 | N5: =+M5 -> 2000 | O5: =+N5 -> 2000
C6: tbd | G6: 0 | H6: =+G6 -> 0 | I6: =+H6 -> 0 | J6: =+I6 -> 0 | K6: 0 | L6: 0 | M6: 0 | N6: 0 | O6: 0
C7: tbd | G7: 0 | H7: =+G7 -> 0 | I7: =+H7 -> 0 | J7: =+I7 -> 0 | K7: 0 | L7: 0 | M7: 0 | N7: 0 | O7: 0
B8: Total Debt | G8: =SUM(G3:G7) -> 6500 | H8: =SUM(H3:H7) -> 6250 | I8: =SUM(I3:I7) -> 5550 | J8: =SUM(J3:J7) -> 5250 | K8: =SUM(K3:K7) -> 5000 | L8: =SUM(L3:L7) -> 4750 | M8: =SUM(M3:M7) -> 4500 | N8: =SUM(N3:N7) -> 4250 | O8: =SUM(O3:O7) -> 4000
B10: Current Portion Calculation
C11: Short Term | G11: =+G8-H8 -> 250 | H11: =+H8-I8 -> 700 | I11: =+I8-J8 -> 300 | J11: =+J8-K8 -> 250 | K11: =+K8-L8 -> 250 | L11: =+L8-M8 -> 250 | M11: =+M8-N8 -> 250 | N11: =+N8-O8 -> 250
C12: Long Term | G12: =+G8-G11 -> 6250 | H12: =+H8-H11 -> 5550 | I12: =+I8-I11 -> 5250 | J12: =+J8-J11 -> 5000 | K12: =+K8-K11 -> 4750 | L12: =+L8-L11 -> 4500 | M12: =+M8-M11 -> 4250 | N12: =+N8-N11 -> 4000
B14: Interest Rates
C15: {=+C3:C7} -> Hunington Revolver | G15: 0.075 | H15: 0.076 | I15: 0.0765 | J15: =+I15 -> 0.0765 | K15: =+J15 -> 0.0765 | L15: =+K15 -> 0.0765 | M15: =+L15 -> 0.0765 | N15: =+M15 -> 0.0765
C16: PNC Term Loan | G16: 0.0575 | H16: 0.0575 | I16: 0.0575 | J16: =+I16 -> 0.0575 | K16: =+J16 -> 0.0575 | L16: =+K16 -> 0.0575 | M16: =+L16 -> 0.0575 | N16: =+M16 -> 0.0575
C17: Key Bank Term Loan | G17: 0.045 | H17: 0.055 | I17: 0.065 | J17: =+I17 -> 0.065 | K17: =+J17 -> 0.065 | L17: =+K17 -> 0.065 | M17: =+L17 -> 0.065 | N17: =+M17 -> 0.065
C18: tbd | G18: 9.99 | H18: 9.99 | I18: 9.99 | J18: =+I18 -> 9.99 | K18: =+J18 -> 9.99 | L18: =+K18 -> 9.99 | M18: =+L18 -> 9.99 | N18: =+M18 -> 9.99
C19: tbd | G19: 9.99 | H19: 9.99 | I19: 9.99 | J19: =+I19 -> 9.99 | K19: =+J19 -> 9.99 | L19: =+K19 -> 9.99 | M19: =+L19 -> 9.99 | N19: =+M19 -> 9.99
B21: Interest Expense | G21: {=SUMPRODUCT(G3:G7*G15:G19)} -> 355.625 | H21: {=SUMPRODUCT(H3:H7*H15:H19)} -> 367 | I21: {=SUMPRODUCT(I3:I7*I15:I19)} -> 348.375 | J21: {=SUMPRODUCT(J3:J7*J15:J19)} -> 331.125 | K21: {=SUMPRODUCT(K3:K7*K15:K19)} -> 316.75 | L21: {=SUMPRODUCT(L3:L7*L15:L19)} -> 302.375 | M21: {=SUMPRODUCT(M3:M7*M15:M19)} -> 288 | N21: {=SUMPRODUCT(N3:N7*N15:N19)} -> 273.625
